audio_glitch_detector/__init__.py
audio_glitch_detector/cli.py
audio_glitch_detector/file_mode.py
audio_glitch_detector/stream_mode.py
audio_glitch_detector/audio/__init__.py
audio_glitch_detector/audio/block_saver.py
audio_glitch_detector/audio/config.py
audio_glitch_detector/audio/devices.py
audio_glitch_detector/audio/glitch_queue.py
audio_glitch_detector/core/__init__.py
audio_glitch_detector/core/analysis.py
audio_glitch_detector/core/detector.py
audio_glitch_detector/readers/__init__.py
audio_glitch_detector/readers/file_reader.py
audio_glitch_detector/readers/stream_reader.py
audio_glitch_detector/tui/__init__.py
audio_glitch_detector/tui/console_output.py
audio_glitch_detector/utils/__init__.py
audio_glitch_detector/utils/time_utils.py
audio_glitch_detector-0.2.1.dist-info/METADATA
audio_glitch_detector-0.2.1.dist-info/WHEEL
audio_glitch_detector-0.2.1.dist-info/entry_points.txt
audio_glitch_detector-0.2.1.dist-info/licenses/LICENSE
audio_glitch_detector-0.2.1.dist-info/RECORD
