Metadata-Version: 2.4
Name: audio-glitch-detector
Version: 0.2.1
Summary: Detect audio glitches and discontinuities in sinusoidal audio signals
Project-URL: Homepage, https://github.com/kaspernyhus/audio-glitch-detector
Project-URL: Repository, https://github.com/kaspernyhus/audio-glitch-detector
Project-URL: Issues, https://github.com/kaspernyhus/audio-glitch-detector/issues
Author-email: Kasper Nyhus <kanyhus@gmail.com>
License: MIT
License-File: LICENSE
Keywords: audio,cli,detection,glitch,signal-processing
Requires-Python: >=3.12
Requires-Dist: matplotlib>=3.5.0
Requires-Dist: numpy>=1.24.0
Requires-Dist: pyaudio>=0.2.14
Requires-Dist: rich>=13.0.0
Requires-Dist: soundfile>=0.12.0
Requires-Dist: tqdm>=4.65.0
